README.rst
setup.cfg
setup.py
pyregdom.egg-info/PKG-INFO
pyregdom.egg-info/SOURCES.txt
pyregdom.egg-info/dependency_links.txt
pyregdom.egg-info/not-zip-safe
pyregdom.egg-info/top_level.txt
regdom/__init__.py
regdom/effective_tlds.py
regdom/reg_domain.py