Metadata-Version: 1.1
Name: pyregdom
Version: 0.4-2
Summary: Detect the registered domains for given hostnames based on Mozillas effective TLD listing
Home-page: https://github.com/huyphan/pyregdom
Author: Huy Phan
Author-email: dachuy@gmail.com
License: Apache 2.0
Platform: UNKNOWN
Classifier: Development Status :: 3 - Alpha
Classifier: Intended Audience :: Developers
Classifier: Natural Language :: English
Classifier: License :: OSI Approved :: Apache Software License
Classifier: Programming Language :: Python
Classifier: Programming Language :: Python :: 2.6
Classifier: Programming Language :: Python :: 2.7
